<?xml version="1.0" encoding="utf-8"?>
<odoo>

    <!-- ## SOLICITUD ESCUELA ROL ADMIN ## -->
    <!-- <record id="admin_berp_solicitud_escuela" model="ir.model.access">
        <field name="name">admin_berp_solicitud_escuela</field>
        <field name="model_id" ref="model_berp_solicitud_escuela"/>
        <field name="group_id" ref="berp.berp_admin"/>
        <field name="perm_read" eval="1"/>
        <field name="perm_write" eval="1"/>
        <field name="perm_create" eval="1"/>
        <field name="perm_unlink" eval="1" />
    </record> -->

    <!-- ## SOLICITUD ESCUELA ROL ESCUELA ## -->
    <!-- <record id="admin_berp_solicitud_escuela" model="ir.model.access">
        <field name="name">admin_berp_solicitud_escuela</field>
        <field name="model_id" ref="model_berp_solicitud_escuela"/>
        <field name="group_id" ref="berp.berp_escuela"/>
        <field name="perm_read" eval="1"/>
        <field name="perm_write" eval="1"/>
        <field name="perm_create" eval="0"/>
        <field name="perm_unlink" eval="0" />
    </record> -->

</odoo>